MANIFEST.in
README.md
setup.cfg
setup.py
bin/blabla
blabla/__init__.py
blabla/document_engine.py
blabla/document_processor.py
blabla.egg-info/PKG-INFO
blabla.egg-info/SOURCES.txt
blabla.egg-info/dependency_links.txt
blabla.egg-info/not-zip-safe
blabla.egg-info/requires.txt
blabla.egg-info/top_level.txt
blabla/language_resources/__init__.py
blabla/language_resources/ar_properties.txt
blabla/language_resources/de_properties.txt
blabla/language_resources/en_properties.txt
blabla/language_resources/es_properties.txt
blabla/language_resources/fr_properties.txt
blabla/language_resources/zh-hant_properties.txt
blabla/sentence_aggregators/__init__.py
blabla/sentence_aggregators/discourse_and_pragmatic_feature_aggregator.py
blabla/sentence_aggregators/lexico_semantic_fearture_aggregator.py
blabla/sentence_aggregators/morpho_syntactic_feature_aggregator.py
blabla/sentence_aggregators/phonetic_and_phonological_feature_aggregator.py
blabla/sentence_aggregators/phonetic_features_settings.py
blabla/sentence_aggregators/syntactic_feature_aggregator.py
blabla/sentence_processor/__init__.py
blabla/sentence_processor/discourse_and_pragmatic_feature_engine.py
blabla/sentence_processor/lexico_semantic_feature_engine.py
blabla/sentence_processor/morpho_syntactic_feature_engine.py
blabla/sentence_processor/pos_tag_counting_engine.py
blabla/sentence_processor/sentence_processing_engine.py
blabla/sentence_processor/syntactic_feature_engine.py
blabla/sentence_processor/yngve_tree.py
blabla/utils/__init__.py
blabla/utils/exceptions.py
blabla/utils/global_params.py
blabla/utils/settings.py