Metadata-Version: 1.1
Name: blabla
Version: 0.2.2
Summary: Novoic linguistics feature extraction package.
Home-page: http://github.com/novoic/BlaBla
Author: Abhishek Shivkumar
Author-email: abhishek@novoic.com
License: GPL-3.0
Download-URL: https://github.com/novoic/blabla/archive/v0.2.2.tar.gz
Keywords: feature-extraction,language,machine-learning,text-processing,python,natural-language-processing,nlp,stanza,dementia,alzheimers-disease,parkinsons-disease
Platform: UNKNOWN
Classifier: Development Status :: 4 - Beta
Classifier: Intended Audience :: Healthcare Industry
Classifier: Topic :: Scientific/Engineering :: Bio-Informatics
Classifier: License :: OSI Approved :: GNU General Public License v3 (GPLv3)
Classifier: Programming Language :: Python :: 3.6
Classifier: Programming Language :: Python :: 3.7
